gos/__init__.py
gos/configuration.py
gos/exceptions.py
gos/executable_containers.py
gos/manager.py
gos/tasks.py
gos/algo/__init__.py
gos/algo/executable_containers/__init__.py
gos/algo/executable_containers/base_round.py
gos/algo/executable_containers/base_stage.py
gos/algo/executable_containers/pipeline.py
gos/utils/__init__.py
gos/utils/load.py
gos-0.9.dist-info/METADATA
gos-0.9.dist-info/RECORD
gos-0.9.dist-info/WHEEL
gos-0.9.dist-info/top_level.txt
tests/__init__.py
tests/test_configuration.py
tests/test_executable_containers.py
tests/test_manager.py
tests/test_tasks.py
