Metadata-Version: 2.1
Name: gos
Version: 0.9
Summary: Generically organizable supervisor to create multi-level executable pipelines
Home-page: https://github.com/aganezov/gos
Author: Sergey Aganezov
Author-email: aganezov@cs.jhu.edu
License: MIT
Keywords: pipeline,data structures,python
Platform: UNKNOWN
Classifier: Development Status :: 4 - Beta
Classifier: License :: OSI Approved :: MIT License
Classifier: Programming Language :: Python
Classifier: Programming Language :: Python :: 2
Classifier: Programming Language :: Python :: 2.7
Classifier: Programming Language :: Python :: 3
Classifier: Programming Language :: Python :: 3.3
Classifier: Programming Language :: Python :: 3.4
Classifier: Programming Language :: Python :: 3.5
